MANIFEST.in
README.txt
setup.py
c2/__init__.py
c2.splitter.twocharacters.egg-info/PKG-INFO
c2.splitter.twocharacters.egg-info/SOURCES.txt
c2.splitter.twocharacters.egg-info/dependency_links.txt
c2.splitter.twocharacters.egg-info/entry_points.txt
c2.splitter.twocharacters.egg-info/namespace_packages.txt
c2.splitter.twocharacters.egg-info/not-zip-safe
c2.splitter.twocharacters.egg-info/requires.txt
c2.splitter.twocharacters.egg-info/top_level.txt
c2/splitter/__init__.py
c2/splitter/twocharacters/__init__.py
c2/splitter/twocharacters/configure.zcml
c2/splitter/twocharacters/tests.py
c2/splitter/twocharacters/twochara.py
c2/splitter/twocharacters/version.txt
docs/HISTORY.txt
docs/INSTALL.txt
docs/LICENSE.GPL
docs/LICENSE.txt