Metadata-Version: 1.1
Name: c2.splitter.twocharacters
Version: 1.0a1
Summary: This product is split word to two characters for Plone.
Home-page: https://www.cmscom.jp
Author: Manabu TERADA
Author-email: terada@cmscom.jp
License: GPL
Keywords: plone splitter
Platform: UNKNOWN
Classifier: Framework :: Plone
Classifier: Programming Language :: Python
